netcfg_builder/__init__.py
netcfg_builder/build.py
netcfg_builder/cli.py
netcfg_builder/netbox.py
netcfg_builder/variables.py
netcfg_builder-0.3.0.dist-info/METADATA
netcfg_builder-0.3.0.dist-info/WHEEL
netcfg_builder-0.3.0.dist-info/entry_points.txt
netcfg_builder-0.3.0.dist-info/top_level.txt
netcfg_builder-0.3.0.dist-info/RECORD
