Metadata-Version: 2.1
Name: netcfg-builder
Version: 0.3.0
Summary: Network Config Builder
Home-page: UNKNOWN
Author: Jeremy Schulman
License: UNKNOWN
Platform: UNKNOWN
Classifier: Development Status :: 3 - Alpha
Classifier: Programming Language :: Python :: 3.8
Classifier: Topic :: Software Development :: Libraries :: Python Modules
Classifier: Topic :: System :: Networking
Requires-Dist: click
Requires-Dist: jinja2
Requires-Dist: httpx
Requires-Dist: envtoml
Requires-Dist: envyaml
Requires-Dist: tenacity
